DChemPy/Chem.py
DChemPy/Dataset.py
DChemPy/Drawing.py
DChemPy/Featurization.py
DChemPy/Statistic.py
DChemPy/__init__.py
dchempy-1.1.1.dist-info/METADATA
dchempy-1.1.1.dist-info/WHEEL
dchempy-1.1.1.dist-info/licenses/LICENSE
dchempy-1.1.1.dist-info/RECORD
